{"symbol":"SREEL","count":1,"rows":[{"symbol":"SREEL","scripCode":"535601","company":"Sreeleathers Ltd","insider":"","category":"Insider Trading / SAST","type":"","txnType":"","quantity":0,"value":0,"fromDate":"","toDate":"","headline":"Closure of trading window SEBI(PIT) Regulations, 2015 for the quarter and year ended 31.03.2026.","subcategory":"Closure of Trading Window","intimationDate":"2026-03-31T18:18:52.643","broadcastDate":"2026-03-31T18:18:52.643","attachmentName":"e1eaf39a-891f-471b-a456-ae8452625237.pdf","attachmentUrl":"https://www.bseindia.com/xml-data/corpfiling/AttachHis/e1eaf39a-891f-471b-a456-ae8452625237.pdf","attachmentBytes":84703,"pdfFlag":true,"newsId":"ba1b2031-b156-4af8-b37e-617d112bc8c3"}]}