{"symbol":"CCHHL","count":1,"rows":[{"symbol":"CCHHL","scripCode":"526550","company":"Country Club Hospitality & Holidays Ltd","insider":"","category":"Insider Trading / SAST","type":"","txnType":"","quantity":0,"value":0,"fromDate":"","toDate":"","headline":"Pursuant to the Provisions of Prevention of Insider Trading and in terms of SEBI (Prohibition of Insider Trading) Regulations, 2015, this is to inform you that Trading Window for dealing ....","subcategory":"Closure of Trading Window","intimationDate":"2026-03-31T17:22:13.307","broadcastDate":"2026-03-31T17:22:13.307","attachmentName":"dffe16d1-403a-4912-bb42-7d568f57ab25.pdf","attachmentUrl":"https://www.bseindia.com/xml-data/corpfiling/AttachHis/dffe16d1-403a-4912-bb42-7d568f57ab25.pdf","attachmentBytes":1306710,"pdfFlag":true,"newsId":"d60f04ad-19b3-4684-ada4-4eaaf29954af"}]}