{"symbol":"NAVINFLUOR","source":"Screener.in","updated":"2026-05-16T06:56:32+00:00","screenerCompanyId":"2217","categories":{"foreign_institutions":{"Government Pension Fund Global":{"Dec 2023":"1.37","Mar 2024":"2.05","Jun 2024":"2.25","Sep 2024":"2.25","Dec 2024":"2.99","Mar 2025":"3.20","Jun 2025":"3.20","Sep 2025":"3.57","Dec 2025":"3.57","Mar 2026":"3.92","__personUrl":"/people/84688/government-pension-fund-global/"},"Smallcap World Fund, Inc":{"Jun 2023":"2.79","Sep 2023":"2.79","Dec 2023":"1.27","__personUrl":"/people/436/smallcap-world-fund-inc/"},"Kotak Funds - India Midcap Fund":{"Jun 2025":"1.21","Sep 2025":"1.33","Dec 2025":"1.37","Mar 2026":"1.38","__personUrl":"/people/93849/kotak-funds-india-midcap-fund/"},"Goldman Sachs Funds - Goldman Sachs India Equity":{"Dec 2024":"1.01","Mar 2025":"1.43","Jun 2025":"1.43","Sep 2025":"1.62","Dec 2025":"1.29","Mar 2026":"1.06","__personUrl":"/people/163789/goldman-sachs-funds-goldman-sachs-india-equity/"},"Abu Dhabi Investment Authority":{"Jun 2025":"1.12","Sep 2025":"1.31","Dec 2025":"1.23","__personUrl":"/people/433/abu-dhabi-investment-authority/"},"Vanguard Total International Stock Index Fund":{"Dec 2025":"1.01","Mar 2026":"1.02","__personUrl":"/people/166712/vanguard-total-international-stock-index-fund/"}},"domestic_institutions":{"Life Insurance Corporation Of India\t":{"Jun 2023":"1.40","Sep 2023":"2.20","Dec 2023":"4.55","Mar 2024":"8.97","Jun 2024":"9.75","Sep 2024":"10.08","Dec 2024":"10.08","Mar 2025":"9.81","Jun 2025":"7.85","Sep 2025":"7.35","Dec 2025":"6.43","Mar 2026":"5.20","__personUrl":"/people/123150/life-insurance-corporation-of-india/"},"Icici Prudential Mutual Funds\t":{"Dec 2023":"1.85","Mar 2024":"3.09","Jun 2024":"2.79","Sep 2024":"2.78","Dec 2024":"3.95","Mar 2025":"3.10","Jun 2025":"1.57","Sep 2025":"1.40","__personUrl":"/people/47312/icici-prudential-mutual-funds/"},"Sbi Mutual Funds\t":{"Jun 2023":"2.82","Sep 2023":"1.43","Dec 2023":"1.49","Mar 2024":"1.55","Jun 2024":"1.46","Sep 2024":"1.68","Dec 2024":"1.66","Mar 2025":"1.83","Jun 2025":"3.91","Sep 2025":"4.06","Dec 2025":"3.80","Mar 2026":"3.80","__personUrl":"/people/52770/sbi-mutual-funds/"},"Axis Mutual Fund Trustee Limited\t":{"Jun 2023":"2.83","Sep 2023":"3.77","Dec 2023":"2.56","Mar 2024":"1.62","Jun 2024":"1.44","Mar 2025":"1.71","Jun 2025":"2.04","Sep 2025":"2.22","Dec 2025":"2.37","Mar 2026":"2.33","__personUrl":"/people/428/axis-mutual-fund-trustee-limited/"},"Nippon Life India Trustee Ltd":{"Jun 2023":"2.72","Sep 2023":"2.72","Dec 2023":"2.26","Mar 2024":"1.10","__personUrl":"/people/361/nippon-life-india-trustee-ltd/"},"Sundaram Mutual Funds\t":{"Jun 2023":"1.82","Sep 2023":"1.82","Dec 2023":"1.48","__personUrl":"/people/51217/sundaram-mutual-funds/"},"Motilal Oswal Mutual Funds":{"Dec 2023":"1.66","__personUrl":"/people/42623/motilal-oswal-mutual-funds/"},"Canara Robeco Mutual Funds":{"Jun 2023":"2.38","Sep 2023":"2.56","Dec 2023":"1.54","Mar 2024":"1.04","Jun 2024":"1.04","Sep 2024":"1.04","__personUrl":"/people/52767/canara-robeco-mutual-funds/"},"Dsp Mutual Funds\t":{"Dec 2024":"1.55","Mar 2025":"1.53","Jun 2025":"1.48","Sep 2025":"1.41","__personUrl":"/people/131758/dsp-mutual-funds/"},"Aditya Birla Sun Life Trustee Private Limited\t":{"Sep 2023":"1.17","Dec 2023":"1.17","Mar 2024":"1.58","Jun 2024":"1.83","Sep 2024":"2.05","Dec 2024":"1.97","Mar 2025":"1.51","Jun 2025":"1.13","Sep 2025":"1.32","Dec 2025":"1.28","Mar 2026":"1.29","__personUrl":"/people/142401/aditya-birla-sun-life-trustee-private-limited/"},"Tata Aia Life Insurance Co Ltd":{"Dec 2023":"1.58","Mar 2024":"1.12","__personUrl":"/people/52393/tata-aia-life-insurance-co-ltd/"},"Nippon Life India Trustee Ltd\t":{"Sep 2025":"1.26","Dec 2025":"1.24","Mar 2026":"1.28","__personUrl":"/people/130524/nippon-life-india-trustee-ltd/"},"Pgim India Trustees Private Limited":{"Jun 2023":"1.06","Sep 2023":"1.08","Dec 2023":"1.42","Mar 2024":"1.37","__personUrl":"/people/7429/pgim-india-trustees-private-limited/"},"Edelweiss Mutual Funds":{"Mar 2025":"1.21","Jun 2025":"1.17","Sep 2025":"1.25","Dec 2025":"1.31","Mar 2026":"1.09","__personUrl":"/people/168211/edelweiss-mutual-funds/"},"Hsbc Mutual Funds":{"Jun 2023":"1.13","__personUrl":"/people/126533/hsbc-mutual-funds/"},"Baroda Bnp Paribas Elss Fund":{"Mar 2026":"1.13","__personUrl":"/people/191887/baroda-bnp-paribas-elss-fund/"},"Mirae Asset Mutual Funds":{"Jun 2024":"1.03","__personUrl":"/people/153130/mirae-asset-mutual-funds/"}}}}