{"symbol":"ONGC","source":"Screener.in","updated":"2026-05-16T06:57:21+00:00","count":12,"quarters":[{"period":"Jun 2023","periodIso":"2023-06-30","promoter":58.89,"fii":8.11,"dii":19.84,"public":2.87,"government":10.3,"others":0.0},{"period":"Sep 2023","periodIso":"2023-09-30","promoter":58.89,"fii":8.38,"dii":19.58,"public":2.83,"government":10.3,"others":0.0},{"period":"Dec 2023","periodIso":"2023-12-31","promoter":58.89,"fii":9.2,"dii":18.73,"public":2.89,"government":10.3,"others":0.0},{"period":"Mar 2024","periodIso":"2024-03-31","promoter":58.89,"fii":8.88,"dii":18.88,"public":3.05,"government":10.3,"others":0.0},{"period":"Jun 2024","periodIso":"2024-06-30","promoter":58.89,"fii":8.57,"dii":18.75,"public":3.5,"government":10.3,"others":0.0},{"period":"Sep 2024","periodIso":"2024-09-30","promoter":58.89,"fii":8.12,"dii":19.04,"public":3.65,"government":10.3,"others":0.0},{"period":"Dec 2024","periodIso":"2024-12-31","promoter":58.89,"fii":7.53,"dii":19.4,"public":3.88,"government":10.3,"others":0.0},{"period":"Mar 2025","periodIso":"2025-03-31","promoter":58.89,"fii":7.11,"dii":19.93,"public":3.76,"government":10.3,"others":0.0},{"period":"Jun 2025","periodIso":"2025-06-30","promoter":58.89,"fii":7.08,"dii":19.85,"public":3.88,"government":10.3,"others":0.0},{"period":"Sep 2025","periodIso":"2025-09-30","promoter":58.89,"fii":6.98,"dii":19.96,"public":3.87,"government":10.3,"others":0.0},{"period":"Dec 2025","periodIso":"2025-12-31","promoter":58.89,"fii":7.43,"dii":19.69,"public":3.69,"government":10.3,"others":0.0},{"period":"Mar 2026","periodIso":"2026-03-31","promoter":58.89,"fii":7.97,"dii":19.3,"public":3.54,"government":10.3,"others":0.0}]}