{"symbol":"GSFC","count":1,"rows":[{"symbol":"GSFC","scripCode":"500690","company":"Gujarat State Fertilizers & Chemicals Ltd","insider":"","category":"Insider Trading / SAST","type":"","txnType":"","quantity":0,"value":0,"fromDate":"","toDate":"","headline":"Intimation of Closure of Trading windows for dealing in securities of the Company has been closed from 23.03.2026 and shall remain closed till 48 hours after the announcement of financial ....","subcategory":"Closure of Trading Window","intimationDate":"2026-05-05T11:32:41.77","broadcastDate":"2026-05-05T11:32:41.77","attachmentName":"ee4aa368-807d-4b13-a68a-12732f870c3a.pdf","attachmentUrl":"https://www.bseindia.com/xml-data/corpfiling/AttachHis/ee4aa368-807d-4b13-a68a-12732f870c3a.pdf","attachmentBytes":685277,"pdfFlag":true,"newsId":"f4bbd508-3f18-4770-a484-c1faa0178e50"}]}