{"symbol":"POWERGRID","source":"Screener.in","updated":"2026-05-16T06:59:59+00:00","count":12,"quarters":[{"period":"Jun 2023","periodIso":"2023-06-30","promoter":51.34,"fii":33.14,"dii":12.55,"public":2.95,"government":0.0,"others":0.0},{"period":"Sep 2023","periodIso":"2023-09-30","promoter":51.34,"fii":32.01,"dii":13.21,"public":3.44,"government":0.0,"others":0.0},{"period":"Dec 2023","periodIso":"2023-12-31","promoter":51.34,"fii":30.51,"dii":14.77,"public":3.37,"government":0.0,"others":0.0},{"period":"Mar 2024","periodIso":"2024-03-31","promoter":51.34,"fii":29.82,"dii":15.26,"public":3.58,"government":0.0,"others":0.0},{"period":"Jun 2024","periodIso":"2024-06-30","promoter":51.34,"fii":28.73,"dii":16.32,"public":3.61,"government":0.0,"others":0.0},{"period":"Sep 2024","periodIso":"2024-09-30","promoter":51.34,"fii":28.26,"dii":16.89,"public":3.5,"government":0.0,"others":0.0},{"period":"Dec 2024","periodIso":"2024-12-31","promoter":51.34,"fii":28.11,"dii":16.99,"public":3.5,"government":0.04,"others":0.0},{"period":"Mar 2025","periodIso":"2025-03-31","promoter":51.34,"fii":26.79,"dii":18.3,"public":3.52,"government":0.06,"others":0.0},{"period":"Jun 2025","periodIso":"2025-06-30","promoter":51.34,"fii":26.5,"dii":18.49,"public":3.61,"government":0.07,"others":0.0},{"period":"Sep 2025","periodIso":"2025-09-30","promoter":51.34,"fii":25.66,"dii":19.33,"public":3.6,"government":0.07,"others":0.0},{"period":"Dec 2025","periodIso":"2025-12-31","promoter":51.34,"fii":24.73,"dii":20.19,"public":3.67,"government":0.07,"others":0.0},{"period":"Mar 2026","periodIso":"2026-03-31","promoter":51.34,"fii":25.02,"dii":20.05,"public":3.51,"government":0.08,"others":0.0}]}