{"symbol":"PRIMO","count":62,"rows":[{"date":"2026-02-09","open":22.55,"high":22.55,"low":22.0,"close":22.27,"volume":56452},{"date":"2026-02-10","open":22.0,"high":22.85,"low":22.0,"close":22.25,"volume":58377},{"date":"2026-02-11","open":22.25,"high":22.85,"low":21.5,"close":22.32,"volume":104534},{"date":"2026-02-12","open":22.77,"high":22.77,"low":21.5,"close":22.02,"volume":25181},{"date":"2026-02-13","open":22.01,"high":22.31,"low":21.62,"close":21.85,"volume":50428},{"date":"2026-02-16","open":21.85,"high":22.63,"low":20.73,"close":22.14,"volume":95752},{"date":"2026-02-17","open":22.25,"high":22.34,"low":21.61,"close":22.01,"volume":78462},{"date":"2026-02-18","open":22.13,"high":22.49,"low":21.31,"close":22.04,"volume":142180},{"date":"2026-02-19","open":22.04,"high":22.04,"low":20.74,"close":20.82,"volume":70843},{"date":"2026-02-20","open":21.6,"high":21.8,"low":20.51,"close":20.77,"volume":189348},{"date":"2026-02-23","open":20.88,"high":21.49,"low":19.78,"close":20.08,"volume":63217},{"date":"2026-02-24","open":20.0,"high":20.28,"low":19.75,"close":19.94,"volume":30888},{"date":"2026-02-25","open":19.85,"high":20.1,"low":19.65,"close":19.93,"volume":77727},{"date":"2026-02-26","open":20.09,"high":20.09,"low":19.3,"close":19.43,"volume":76784},{"date":"2026-02-27","open":19.7,"high":20.04,"low":18.42,"close":18.72,"volume":119838},{"date":"2026-03-02","open":17.3,"high":18.8,"low":17.3,"close":18.46,"volume":91170},{"date":"2026-03-04","open":17.3,"high":18.45,"low":17.3,"close":18.09,"volume":120299},{"date":"2026-03-05","open":18.9,"high":18.9,"low":17.53,"close":18.04,"volume":247786},{"date":"2026-03-06","open":18.04,"high":18.5,"low":18.01,"close":18.1,"volume":47509},{"date":"2026-03-09","open":18.1,"high":18.1,"low":16.78,"close":17.08,"volume":182930},{"date":"2026-03-10","open":17.25,"high":18.05,"low":16.82,"close":17.29,"volume":128758},{"date":"2026-03-11","open":17.64,"high":17.87,"low":17.1,"close":17.32,"volume":295738},{"date":"2026-03-12","open":17.67,"high":17.85,"low":17.25,"close":17.35,"volume":225781},{"date":"2026-03-13","open":17.01,"high":20.19,"low":17.01,"close":18.11,"volume":305189},{"date":"2026-03-16","open":17.2,"high":20.0,"low":17.2,"close":17.96,"volume":279153},{"date":"2026-03-17","open":19.1,"high":19.1,"low":17.42,"close":17.77,"volume":125625},{"date":"2026-03-18","open":17.35,"high":18.53,"low":17.35,"close":18.02,"volume":183152},{"date":"2026-03-19","open":17.2,"high":18.61,"low":17.2,"close":18.05,"volume":170224},{"date":"2026-03-20","open":18.05,"high":18.47,"low":18.0,"close":18.1,"volume":271408},{"date":"2026-03-23","open":18.1,"high":18.29,"low":16.36,"close":16.85,"volume":282557},{"date":"2026-03-24","open":17.24,"high":17.29,"low":16.1,"close":17.01,"volume":304995},{"date":"2026-03-25","open":16.96,"high":17.46,"low":16.82,"close":16.91,"volume":381212},{"date":"2026-03-27","open":16.91,"high":19.07,"low":16.27,"close":17.31,"volume":837802},{"date":"2026-03-30","open":17.08,"high":19.5,"low":16.76,"close":18.03,"volume":479519},{"date":"2026-04-01","open":18.88,"high":19.53,"low":18.26,"close":19.15,"volume":203545},{"date":"2026-04-02","open":19.48,"high":22.0,"low":19.12,"close":21.42,"volume":366200},{"date":"2026-04-06","open":21.8,"high":23.52,"low":21.8,"close":22.22,"volume":423415},{"date":"2026-04-07","open":22.64,"high":23.39,"low":22.2,"close":22.66,"volume":365913},{"date":"2026-04-08","open":23.29,"high":23.48,"low":22.05,"close":22.27,"volume":133099},{"date":"2026-04-09","open":22.0,"high":22.61,"low":21.9,"close":22.27,"volume":89063},{"date":"2026-04-10","open":22.87,"high":23.19,"low":22.68,"close":22.97,"volume":295835},{"date":"2026-04-13","open":22.51,"high":23.03,"low":21.96,"close":22.86,"volume":89701},{"date":"2026-04-15","open":23.6,"high":23.9,"low":22.57,"close":23.35,"volume":113744},{"date":"2026-04-16","open":23.4,"high":25.0,"low":23.15,"close":24.63,"volume":456680},{"date":"2026-04-17","open":24.63,"high":25.16,"low":23.86,"close":24.2,"volume":280944},{"date":"2026-04-20","open":24.2,"high":24.2,"low":23.5,"close":23.69,"volume":130831},{"date":"2026-04-21","open":23.84,"high":23.92,"low":23.06,"close":23.24,"volume":139743},{"date":"2026-04-22","open":23.54,"high":24.8,"low":22.32,"close":24.25,"volume":728100},{"date":"2026-04-23","open":24.68,"high":24.8,"low":23.88,"close":24.29,"volume":322350},{"date":"2026-04-24","open":24.0,"high":24.54,"low":23.16,"close":23.37,"volume":159194},{"date":"2026-04-27","open":23.84,"high":24.4,"low":23.2,"close":23.7,"volume":166930},{"date":"2026-04-28","open":23.7,"high":24.24,"low":23.37,"close":23.66,"volume":176591},{"date":"2026-04-29","open":23.84,"high":23.84,"low":22.62,"close":22.81,"volume":202284},{"date":"2026-04-30","open":23.49,"high":23.49,"low":22.31,"close":22.98,"volume":48492},{"date":"2026-05-04","open":22.98,"high":25.99,"low":22.98,"close":25.56,"volume":1174488},{"date":"2026-05-05","open":25.6,"high":25.98,"low":24.73,"close":25.53,"volume":444327},{"date":"2026-05-06","open":26.5,"high":26.8,"low":24.8,"close":24.99,"volume":372547},{"date":"2026-05-07","open":25.4,"high":25.4,"low":24.56,"close":25.07,"volume":406339},{"date":"2026-05-08","open":25.19,"high":25.29,"low":24.56,"close":24.89,"volume":136853},{"date":"2026-05-11","open":24.89,"high":26.9,"low":24.31,"close":26.07,"volume":658487},{"date":"2026-05-12","open":26.1,"high":26.53,"low":25.04,"close":25.65,"volume":428391},{"date":"2026-05-13","open":25.15,"high":25.99,"low":24.71,"close":25.42,"volume":188714}]}