{"symbol":"USK","count":18,"rows":[{"date":"2026-02-09","open":21.48,"high":21.6,"low":20.62,"close":21.41,"volume":42959},{"date":"2026-02-10","open":20.4,"high":21.43,"low":19.5,"close":20.74,"volume":113172},{"date":"2026-02-11","open":20.74,"high":21.39,"low":20.62,"close":21.23,"volume":49713},{"date":"2026-02-12","open":21.98,"high":21.98,"low":20.6,"close":21.13,"volume":49779},{"date":"2026-02-13","open":21.0,"high":21.9,"low":20.66,"close":21.32,"volume":37035},{"date":"2026-02-16","open":21.32,"high":21.77,"low":20.85,"close":21.08,"volume":38667},{"date":"2026-02-17","open":20.82,"high":22.89,"low":20.82,"close":22.47,"volume":146778},{"date":"2026-02-18","open":23.49,"high":24.7,"low":23.4,"close":24.28,"volume":167811},{"date":"2026-02-19","open":25.49,"high":26.49,"low":25.49,"close":25.93,"volume":182378},{"date":"2026-02-20","open":27.1,"high":29.0,"low":26.8,"close":28.2,"volume":476642},{"date":"2026-02-23","open":29.4,"high":29.76,"low":27.21,"close":29.55,"volume":287449},{"date":"2026-02-24","open":30.44,"high":30.9,"low":28.02,"close":28.24,"volume":360058},{"date":"2026-02-25","open":29.5,"high":29.95,"low":29.03,"close":29.77,"volume":154199},{"date":"2026-02-26","open":30.84,"high":30.84,"low":28.01,"close":28.57,"volume":113639},{"date":"2026-02-27","open":29.57,"high":30.2,"low":28.2,"close":28.67,"volume":157291},{"date":"2026-03-02","open":28.67,"high":28.8,"low":26.25,"close":27.51,"volume":109538},{"date":"2026-03-04","open":27.99,"high":28.83,"low":27.23,"close":27.75,"volume":143409},{"date":"2026-03-05","open":28.44,"high":28.51,"low":27.11,"close":27.22,"volume":95521}]}