{"symbol":"CURAA","count":3,"rows":[{"symbol":"CURAA","scripCode":"532332","company":"Cura Technologies Ltd","insider":"","category":"Insider Trading / SAST","type":"","txnType":"","quantity":0,"value":0,"fromDate":"","toDate":"","headline":"Closure of Trading Window","subcategory":"Closure of Trading Window","intimationDate":"2026-03-30T18:45:30.43","broadcastDate":"2026-03-30T18:45:30.43","attachmentName":"fe66e947-3cea-4306-8684-56f102b6d566.pdf","attachmentUrl":"https://www.bseindia.com/xml-data/corpfiling/AttachHis/fe66e947-3cea-4306-8684-56f102b6d566.pdf","attachmentBytes":663390,"pdfFlag":true,"newsId":"79d719cf-0394-46cd-a3b5-cf5797de5e3b"},{"symbol":"CURAA","scripCode":"532332","company":"Cura Technologies Ltd","insider":"","category":"Insider Trading / SAST","type":"","txnType":"","quantity":0,"value":0,"fromDate":"","toDate":"","headline":"The Exchange has received the disclosure under Regulation 29(2) of SEBI (Substantial Acquisition of Shares & Takeovers) Regulations, 2011 for Boosa Ramreddy & PACs","subcategory":"Disclosures under Reg. 29(2) of SEBI (SAST) Regulations, 2011","intimationDate":"2026-03-09T17:03:12.24","broadcastDate":"2026-03-09T17:03:12.24","attachmentName":"12A3B86C_359B_40BB_9777_A5CE818B81A5_170307.pdf","attachmentUrl":"https://www.bseindia.com/xml-data/corpfiling/AttachHis/12A3B86C_359B_40BB_9777_A5CE818B81A5_170307.pdf","attachmentBytes":3707316,"pdfFlag":true,"newsId":"12a3b86c-359b-40bb-9777-a5ce818b81a5"},{"symbol":"CURAA","scripCode":"532332","company":"Cura Technologies Ltd","insider":"","category":"Insider Trading / SAST","type":"","txnType":"","quantity":0,"value":0,"fromDate":"","toDate":"","headline":"The Exchange has received the disclosure under Regulation 29(2) of SEBI (Substantial Acquisition of Shares & Takeovers) Regulations, 2011 for Sanjana Lagumavarapu","subcategory":"Disclosures under Reg. 29(2) of SEBI (SAST) Regulations, 2011","intimationDate":"2026-02-20T10:54:54.3","broadcastDate":"2026-02-20T10:54:54.3","attachmentName":"57B1B737_2353_44E9_A85B_FDE4593098F3_105443.pdf","attachmentUrl":"https://www.bseindia.com/xml-data/corpfiling/AttachHis/57B1B737_2353_44E9_A85B_FDE4593098F3_105443.pdf","attachmentBytes":6708923,"pdfFlag":true,"newsId":"57b1b737-2353-44e9-a85b-fde4593098f3"}]}