{"symbol":"TI","count":1,"rows":[{"symbol":"TI","scripCode":"507205","company":"Tilaknagar Industries Ltd-$","insider":"","category":"Insider Trading / SAST","type":"","txnType":"","quantity":0,"value":0,"fromDate":"","toDate":"","headline":"Pursuant to the provisions of SEBI LODR and the Company''s Code of Conduct for prevention of Insider Trading, the trading window for dealing in the Company''s Equity shares will remain ....","subcategory":"Closure of Trading Window","intimationDate":"2026-03-30T19:13:30.513","broadcastDate":"2026-03-30T19:13:30.513","attachmentName":"022ca8be-421a-468f-bbff-72b076b0add0.pdf","attachmentUrl":"https://www.bseindia.com/xml-data/corpfiling/AttachHis/022ca8be-421a-468f-bbff-72b076b0add0.pdf","attachmentBytes":3584022,"pdfFlag":true,"newsId":"6ee8d715-0fd1-454c-9dc1-c3498f3df1d2"}]}