{"symbol":"SNXT50BETA","count":62,"rows":[{"date":"2026-02-09","open":91.63,"high":93.65,"low":91.0,"close":93.24,"volume":9246},{"date":"2026-02-10","open":93.7,"high":94.97,"low":91.62,"close":93.97,"volume":4109},{"date":"2026-02-11","open":94.77,"high":94.78,"low":92.56,"close":93.61,"volume":3043},{"date":"2026-02-12","open":94.0,"high":94.0,"low":92.36,"close":93.05,"volume":5017},{"date":"2026-02-13","open":93.0,"high":93.0,"low":89.86,"close":91.38,"volume":37146},{"date":"2026-02-16","open":89.09,"high":93.7,"low":89.09,"close":92.25,"volume":7125},{"date":"2026-02-17","open":89.94,"high":93.9,"low":89.94,"close":93.08,"volume":1884},{"date":"2026-02-18","open":93.88,"high":93.88,"low":91.76,"close":93.08,"volume":3839},{"date":"2026-02-19","open":93.08,"high":93.98,"low":91.28,"close":91.7,"volume":4530},{"date":"2026-02-20","open":92.68,"high":92.9,"low":90.2,"close":92.19,"volume":4186},{"date":"2026-02-23","open":93.47,"high":93.65,"low":91.35,"close":91.86,"volume":4383},{"date":"2026-02-24","open":91.88,"high":92.68,"low":90.24,"close":91.9,"volume":2847},{"date":"2026-02-25","open":91.36,"high":95.5,"low":91.36,"close":92.75,"volume":7945},{"date":"2026-02-26","open":90.43,"high":93.85,"low":90.43,"close":92.81,"volume":1927},{"date":"2026-02-27","open":93.08,"high":93.5,"low":91.87,"close":92.24,"volume":3376},{"date":"2026-03-02","open":89.92,"high":93.99,"low":89.5,"close":90.25,"volume":20106},{"date":"2026-03-04","open":92.5,"high":92.5,"low":86.71,"close":88.67,"volume":10088},{"date":"2026-03-05","open":90.17,"high":90.49,"low":88.55,"close":89.47,"volume":2007},{"date":"2026-03-06","open":89.46,"high":89.47,"low":88.07,"close":88.87,"volume":3976},{"date":"2026-03-09","open":90.0,"high":90.0,"low":85.34,"close":86.41,"volume":9429},{"date":"2026-03-10","open":87.97,"high":88.99,"low":86.1,"close":88.56,"volume":2925},{"date":"2026-03-11","open":88.76,"high":89.45,"low":86.93,"close":87.06,"volume":5151},{"date":"2026-03-12","open":87.73,"high":88.67,"low":85.5,"close":86.63,"volume":9873},{"date":"2026-03-13","open":87.27,"high":87.28,"low":82.5,"close":83.98,"volume":27091},{"date":"2026-03-16","open":84.39,"high":85.3,"low":83.11,"close":84.83,"volume":4870},{"date":"2026-03-17","open":84.96,"high":85.0,"low":83.07,"close":84.82,"volume":18561},{"date":"2026-03-18","open":84.82,"high":86.7,"low":84.82,"close":86.52,"volume":3197},{"date":"2026-03-19","open":85.99,"high":85.99,"low":82.15,"close":83.42,"volume":7175},{"date":"2026-03-20","open":85.5,"high":85.7,"low":83.03,"close":83.9,"volume":5307},{"date":"2026-03-23","open":82.99,"high":83.44,"low":80.25,"close":82.02,"volume":8815},{"date":"2026-03-24","open":82.02,"high":83.97,"low":81.01,"close":83.18,"volume":5516},{"date":"2026-03-25","open":84.23,"high":85.25,"low":83.21,"close":84.21,"volume":10503},{"date":"2026-03-27","open":84.98,"high":85.5,"low":82.28,"close":83.08,"volume":6352},{"date":"2026-03-30","open":82.66,"high":83.8,"low":79.55,"close":80.28,"volume":15320},{"date":"2026-04-01","open":77.87,"high":83.69,"low":77.87,"close":83.25,"volume":6956},{"date":"2026-04-02","open":82.81,"high":83.5,"low":79.3,"close":82.28,"volume":67155},{"date":"2026-04-06","open":82.23,"high":85.6,"low":81.05,"close":83.85,"volume":4656},{"date":"2026-04-07","open":83.0,"high":84.9,"low":82.65,"close":83.66,"volume":6169},{"date":"2026-04-08","open":87.67,"high":88.0,"low":85.28,"close":86.39,"volume":10796},{"date":"2026-04-09","open":88.54,"high":88.54,"low":85.61,"close":86.83,"volume":12527},{"date":"2026-04-10","open":86.82,"high":88.58,"low":86.57,"close":88.03,"volume":4058},{"date":"2026-04-13","open":87.99,"high":88.09,"low":85.81,"close":87.81,"volume":5116},{"date":"2026-04-15","open":88.99,"high":89.55,"low":88.07,"close":89.33,"volume":12269},{"date":"2026-04-16","open":89.33,"high":90.52,"low":89.2,"close":90.03,"volume":13792},{"date":"2026-04-17","open":91.3,"high":91.6,"low":89.6,"close":91.27,"volume":6195},{"date":"2026-04-20","open":91.72,"high":92.85,"low":90.5,"close":91.54,"volume":9213},{"date":"2026-04-21","open":92.0,"high":92.0,"low":90.71,"close":91.9,"volume":5349},{"date":"2026-04-22","open":94.19,"high":94.19,"low":89.6,"close":91.93,"volume":3934},{"date":"2026-04-23","open":91.93,"high":92.45,"low":90.56,"close":91.14,"volume":1610},{"date":"2026-04-24","open":91.15,"high":91.89,"low":89.45,"close":90.42,"volume":2963},{"date":"2026-04-27","open":90.41,"high":92.45,"low":90.11,"close":91.68,"volume":3237},{"date":"2026-04-28","open":91.57,"high":91.6,"low":90.31,"close":91.2,"volume":3774},{"date":"2026-04-29","open":91.65,"high":92.5,"low":91.0,"close":91.4,"volume":1388},{"date":"2026-04-30","open":92.57,"high":92.57,"low":89.55,"close":90.44,"volume":7274},{"date":"2026-05-04","open":89.55,"high":91.69,"low":89.1,"close":90.91,"volume":3687},{"date":"2026-05-05","open":88.18,"high":91.3,"low":88.18,"close":91.19,"volume":2508},{"date":"2026-05-06","open":91.64,"high":92.5,"low":90.75,"close":92.16,"volume":3087},{"date":"2026-05-07","open":92.16,"high":93.46,"low":91.32,"close":92.79,"volume":5056},{"date":"2026-05-08","open":91.32,"high":93.47,"low":91.32,"close":92.73,"volume":4413},{"date":"2026-05-11","open":92.69,"high":92.69,"low":91.25,"close":91.54,"volume":2460},{"date":"2026-05-12","open":91.47,"high":91.47,"low":88.5,"close":89.32,"volume":3951},{"date":"2026-05-13","open":89.32,"high":90.76,"low":87.97,"close":89.61,"volume":4609}]}