{"symbol":"NAHARSPING","count":48,"rows":[{"date":"2026-02-09","open":179.54,"high":195.02,"low":178.02,"close":190.95,"volume":112571},{"date":"2026-02-10","open":189.85,"high":195.37,"low":186.26,"close":193.1,"volume":57936},{"date":"2026-02-11","open":195.05,"high":195.35,"low":182.87,"close":191.52,"volume":49325},{"date":"2026-02-12","open":187.99,"high":197.4,"low":186.33,"close":194.07,"volume":47636},{"date":"2026-02-13","open":194.04,"high":209.0,"low":190.0,"close":203.73,"volume":101322},{"date":"2026-02-16","open":202.04,"high":208.25,"low":197.0,"close":197.78,"volume":19676},{"date":"2026-02-17","open":197.78,"high":201.41,"low":197.0,"close":198.08,"volume":23011},{"date":"2026-02-18","open":198.55,"high":208.0,"low":197.62,"close":200.3,"volume":50709},{"date":"2026-02-19","open":203.39,"high":211.4,"low":200.5,"close":208.31,"volume":71131},{"date":"2026-02-20","open":211.4,"high":216.2,"low":207.0,"close":211.31,"volume":80572},{"date":"2026-02-23","open":208.05,"high":209.02,"low":200.22,"close":207.13,"volume":36176},{"date":"2026-02-24","open":206.89,"high":206.89,"low":199.5,"close":200.93,"volume":25235},{"date":"2026-02-25","open":202.87,"high":203.0,"low":198.1,"close":199.75,"volume":27129},{"date":"2026-02-26","open":199.75,"high":205.5,"low":199.75,"close":202.36,"volume":20515},{"date":"2026-02-27","open":202.81,"high":206.99,"low":202.81,"close":204.82,"volume":10708},{"date":"2026-03-02","open":198.0,"high":200.01,"low":192.41,"close":197.98,"volume":20584},{"date":"2026-03-04","open":191.0,"high":196.0,"low":189.26,"close":189.69,"volume":25492},{"date":"2026-03-05","open":191.01,"high":198.9,"low":190.0,"close":196.4,"volume":32407},{"date":"2026-03-06","open":196.04,"high":198.95,"low":193.52,"close":197.34,"volume":16735},{"date":"2026-03-09","open":196.0,"high":196.0,"low":181.12,"close":189.36,"volume":25248},{"date":"2026-03-10","open":192.01,"high":200.7,"low":189.1,"close":199.21,"volume":34025},{"date":"2026-03-11","open":200.7,"high":203.0,"low":192.35,"close":194.87,"volume":22909},{"date":"2026-03-12","open":194.23,"high":198.38,"low":190.97,"close":194.95,"volume":17143},{"date":"2026-03-13","open":197.6,"high":197.78,"low":184.06,"close":185.7,"volume":27732},{"date":"2026-03-16","open":185.94,"high":187.9,"low":182.81,"close":185.64,"volume":17120},{"date":"2026-03-17","open":185.71,"high":202.8,"low":185.71,"close":197.69,"volume":37113},{"date":"2026-03-18","open":196.0,"high":209.85,"low":196.0,"close":206.66,"volume":55861},{"date":"2026-03-19","open":196.0,"high":207.69,"low":196.0,"close":202.63,"volume":30468},{"date":"2026-03-20","open":202.64,"high":214.9,"low":202.64,"close":210.54,"volume":66393},{"date":"2026-03-23","open":211.0,"high":211.0,"low":201.43,"close":202.05,"volume":41165},{"date":"2026-03-24","open":205.1,"high":214.57,"low":202.56,"close":203.41,"volume":23126},{"date":"2026-03-25","open":206.5,"high":211.9,"low":204.0,"close":204.53,"volume":29191},{"date":"2026-03-27","open":199.65,"high":208.0,"low":199.65,"close":205.88,"volume":48049},{"date":"2026-03-30","open":207.0,"high":207.0,"low":195.42,"close":199.99,"volume":37252},{"date":"2026-04-01","open":205.0,"high":218.8,"low":205.0,"close":214.31,"volume":72349},{"date":"2026-04-02","open":213.47,"high":230.0,"low":209.0,"close":227.41,"volume":76616},{"date":"2026-04-06","open":231.0,"high":238.7,"low":223.1,"close":227.18,"volume":29320},{"date":"2026-04-07","open":226.6,"high":229.08,"low":217.63,"close":223.72,"volume":14864},{"date":"2026-04-08","open":233.4,"high":236.6,"low":225.81,"close":232.26,"volume":40377},{"date":"2026-04-09","open":233.0,"high":234.8,"low":228.0,"close":230.15,"volume":15149},{"date":"2026-04-10","open":231.85,"high":241.8,"low":231.5,"close":239.81,"volume":31286},{"date":"2026-04-13","open":237.0,"high":240.89,"low":232.41,"close":237.09,"volume":12732},{"date":"2026-04-15","open":243.0,"high":243.0,"low":235.02,"close":241.66,"volume":30069},{"date":"2026-04-16","open":244.89,"high":253.19,"low":244.02,"close":248.01,"volume":63440},{"date":"2026-04-17","open":248.01,"high":251.5,"low":243.5,"close":249.49,"volume":32648},{"date":"2026-04-20","open":249.0,"high":259.62,"low":244.02,"close":253.81,"volume":63141},{"date":"2026-04-21","open":254.99,"high":259.98,"low":246.55,"close":249.19,"volume":31241},{"date":"2026-04-22","open":254.91,"high":254.91,"low":216.8,"close":238.15,"volume":75763}]}