{"symbol":"BBOX","count":68,"rows":[{"date":"2026-02-09","open":533.45,"high":576.0,"low":526.65,"close":571.15,"volume":836169},{"date":"2026-02-10","open":579.15,"high":580.8,"low":559.25,"close":568.35,"volume":493370},{"date":"2026-02-11","open":568.3,"high":587.0,"low":560.0,"close":582.15,"volume":653829},{"date":"2026-02-12","open":576.95,"high":588.95,"low":547.25,"close":577.75,"volume":1856612},{"date":"2026-02-13","open":561.0,"high":565.2,"low":540.3,"close":544.5,"volume":362873},{"date":"2026-02-16","open":541.75,"high":545.0,"low":521.85,"close":530.4,"volume":710660},{"date":"2026-02-17","open":530.55,"high":542.35,"low":525.25,"close":531.95,"volume":451243},{"date":"2026-02-18","open":532.85,"high":551.3,"low":520.9,"close":529.55,"volume":802221},{"date":"2026-02-19","open":531.8,"high":534.55,"low":511.5,"close":515.35,"volume":456125},{"date":"2026-02-20","open":495.5,"high":522.8,"low":486.0,"close":513.6,"volume":941739},{"date":"2026-02-23","open":523.35,"high":529.65,"low":508.95,"close":518.6,"volume":356304},{"date":"2026-02-24","open":519.95,"high":523.0,"low":507.2,"close":518.65,"volume":475436},{"date":"2026-02-25","open":520.0,"high":553.5,"low":512.35,"close":545.45,"volume":1017209},{"date":"2026-02-26","open":546.0,"high":563.0,"low":531.0,"close":544.85,"volume":581337},{"date":"2026-02-27","open":541.0,"high":543.7,"low":530.0,"close":533.5,"volume":189628},{"date":"2026-03-02","open":510.3,"high":526.95,"low":506.3,"close":515.0,"volume":406250},{"date":"2026-03-04","open":505.0,"high":512.75,"low":502.0,"close":504.95,"volume":247105},{"date":"2026-03-05","open":508.7,"high":516.9,"low":498.0,"close":511.95,"volume":609055},{"date":"2026-03-06","open":511.05,"high":520.0,"low":506.95,"close":512.15,"volume":211256},{"date":"2026-03-09","open":500.0,"high":504.95,"low":488.0,"close":491.55,"volume":216746},{"date":"2026-03-10","open":501.0,"high":516.9,"low":496.7,"close":510.5,"volume":365573},{"date":"2026-03-11","open":514.6,"high":524.4,"low":511.0,"close":514.1,"volume":256482},{"date":"2026-03-12","open":507.0,"high":533.0,"low":505.0,"close":522.15,"volume":307825},{"date":"2026-03-13","open":518.05,"high":521.15,"low":494.0,"close":496.35,"volume":231666},{"date":"2026-03-16","open":496.55,"high":509.0,"low":478.0,"close":496.7,"volume":488853},{"date":"2026-03-17","open":500.0,"high":525.0,"low":492.2,"close":513.45,"volume":589424},{"date":"2026-03-18","open":519.5,"high":528.2,"low":504.1,"close":508.35,"volume":317752},{"date":"2026-03-19","open":499.0,"high":514.9,"low":497.2,"close":499.65,"volume":225455},{"date":"2026-03-20","open":504.9,"high":517.15,"low":495.0,"close":504.35,"volume":305193},{"date":"2026-03-23","open":496.0,"high":499.95,"low":466.75,"close":478.65,"volume":308960},{"date":"2026-03-24","open":495.0,"high":495.55,"low":476.95,"close":482.15,"volume":469716},{"date":"2026-03-25","open":491.2,"high":492.0,"low":475.0,"close":478.8,"volume":334451},{"date":"2026-03-27","open":478.8,"high":479.0,"low":455.25,"close":461.6,"volume":618863},{"date":"2026-03-30","open":455.0,"high":471.9,"low":444.3,"close":447.15,"volume":397247},{"date":"2026-04-01","open":447.4,"high":494.0,"low":447.4,"close":477.55,"volume":420126},{"date":"2026-04-02","open":470.05,"high":474.5,"low":460.0,"close":471.95,"volume":151081},{"date":"2026-04-06","open":472.0,"high":483.75,"low":471.05,"close":476.65,"volume":187940},{"date":"2026-04-07","open":476.5,"high":477.7,"low":468.0,"close":471.6,"volume":169886},{"date":"2026-04-08","open":483.8,"high":501.6,"low":481.0,"close":499.8,"volume":539025},{"date":"2026-04-09","open":503.0,"high":503.0,"low":485.5,"close":488.0,"volume":190108},{"date":"2026-04-10","open":495.0,"high":528.95,"low":493.25,"close":523.75,"volume":620749},{"date":"2026-04-13","open":515.0,"high":526.35,"low":504.0,"close":521.2,"volume":309916},{"date":"2026-04-15","open":530.1,"high":536.0,"low":526.25,"close":532.65,"volume":351582},{"date":"2026-04-16","open":535.8,"high":538.3,"low":528.6,"close":530.3,"volume":330977},{"date":"2026-04-17","open":530.3,"high":546.15,"low":527.0,"close":541.25,"volume":459238},{"date":"2026-04-20","open":542.0,"high":547.2,"low":521.6,"close":526.55,"volume":255393},{"date":"2026-04-21","open":522.8,"high":553.1,"low":520.25,"close":529.4,"volume":424120},{"date":"2026-04-22","open":529.95,"high":535.5,"low":525.0,"close":531.95,"volume":112162},{"date":"2026-04-23","open":531.95,"high":551.0,"low":530.0,"close":548.3,"volume":453944},{"date":"2026-04-24","open":550.0,"high":554.9,"low":535.0,"close":550.1,"volume":346112},{"date":"2026-04-27","open":550.95,"high":581.0,"low":550.95,"close":579.65,"volume":1006912},{"date":"2026-04-28","open":586.0,"high":655.85,"low":582.0,"close":639.85,"volume":8016542},{"date":"2026-04-29","open":637.9,"high":647.5,"low":615.4,"close":618.25,"volume":605951},{"date":"2026-04-30","open":615.0,"high":648.7,"low":615.0,"close":639.6,"volume":1393977},{"date":"2026-05-04","open":647.0,"high":684.9,"low":641.1,"close":661.3,"volume":1553794},{"date":"2026-05-05","open":658.55,"high":705.0,"low":651.55,"close":701.95,"volume":1680098},{"date":"2026-05-06","open":714.0,"high":730.0,"low":705.0,"close":720.45,"volume":1213205},{"date":"2026-05-07","open":718.7,"high":750.0,"low":712.05,"close":736.65,"volume":1107528},{"date":"2026-05-08","open":740.9,"high":762.0,"low":740.0,"close":748.4,"volume":627528},{"date":"2026-05-11","open":759.7,"high":802.0,"low":749.0,"close":788.1,"volume":2113955},{"date":"2026-05-12","open":793.8,"high":872.55,"low":755.8,"close":829.15,"volume":10494889},{"date":"2026-05-13","open":835.0,"high":844.0,"low":807.9,"close":824.9,"volume":1717191},{"date":"2026-05-14","open":823.8,"high":866.0,"low":819.1,"close":853.1,"volume":1848419},{"date":"2026-05-15","open":868.0,"high":885.8,"low":862.35,"close":878.75,"volume":1330155},{"date":"2026-05-18","open":884.0,"high":966.0,"low":840.1,"close":935.2,"volume":3314367},{"date":"2026-05-19","open":940.0,"high":950.2,"low":925.3,"close":945.1,"volume":1061859},{"date":"2026-05-20","open":943.0,"high":959.0,"low":926.3,"close":944.15,"volume":658162},{"date":"2026-05-21","open":954.8,"high":958.3,"low":932.95,"close":952.05,"volume":498376}]}