{"symbol":"KIRLFER","count":23,"rows":[{"date":"2026-04-20","open":443.4,"high":448.0,"low":423.1,"close":427.25,"volume":23647},{"date":"2026-04-21","open":416.9,"high":440.0,"low":416.9,"close":431.15,"volume":37364},{"date":"2026-04-22","open":438.0,"high":443.75,"low":430.0,"close":438.4,"volume":29953},{"date":"2026-04-23","open":440.35,"high":455.45,"low":425.2,"close":429.45,"volume":53084},{"date":"2026-04-24","open":426.0,"high":439.95,"low":415.55,"close":431.15,"volume":42014},{"date":"2026-04-27","open":426.1,"high":448.7,"low":426.1,"close":440.1,"volume":105368},{"date":"2026-04-28","open":440.1,"high":447.95,"low":431.0,"close":434.95,"volume":49732},{"date":"2026-04-29","open":434.95,"high":442.0,"low":431.1,"close":435.6,"volume":42343},{"date":"2026-04-30","open":438.0,"high":438.0,"low":420.55,"close":434.75,"volume":40922},{"date":"2026-05-04","open":441.85,"high":441.9,"low":429.9,"close":436.25,"volume":49810},{"date":"2026-05-05","open":440.0,"high":443.25,"low":428.25,"close":438.25,"volume":52997},{"date":"2026-05-06","open":440.0,"high":469.0,"low":436.0,"close":460.15,"volume":163804},{"date":"2026-05-07","open":468.0,"high":468.0,"low":450.0,"close":453.1,"volume":96764},{"date":"2026-05-08","open":487.0,"high":487.0,"low":441.0,"close":449.7,"volume":255832},{"date":"2026-05-11","open":445.9,"high":460.0,"low":439.8,"close":442.25,"volume":133313},{"date":"2026-05-12","open":442.5,"high":446.95,"low":434.15,"close":439.6,"volume":316726},{"date":"2026-05-13","open":440.0,"high":470.9,"low":440.0,"close":456.1,"volume":230732},{"date":"2026-05-14","open":462.75,"high":462.75,"low":440.5,"close":449.85,"volume":95912},{"date":"2026-05-15","open":448.0,"high":449.9,"low":442.15,"close":446.55,"volume":31339},{"date":"2026-05-18","open":440.0,"high":454.7,"low":421.55,"close":425.95,"volume":87676},{"date":"2026-05-19","open":432.2,"high":433.0,"low":415.0,"close":422.1,"volume":54832},{"date":"2026-05-20","open":422.05,"high":430.0,"low":410.25,"close":422.5,"volume":55994},{"date":"2026-05-21","open":425.0,"high":440.0,"low":423.1,"close":436.2,"volume":67946}]}