{"symbol":"LAL","count":2,"rows":[{"symbol":"LAL","scripCode":"540952","company":"Lorenzini Apparels Ltd","insider":"","category":"Insider Trading / SAST","type":"","txnType":"","quantity":0,"value":0,"fromDate":"","toDate":"","headline":"Closure of Trading Window for the finacial Year ended March 31st 2026.","subcategory":"Closure of Trading Window","intimationDate":"2026-03-27T18:17:18.053","broadcastDate":"2026-03-27T18:17:18.053","attachmentName":"7b31ee6f-950e-4ac8-aa97-d9bbdb16398e.pdf","attachmentUrl":"https://www.bseindia.com/xml-data/corpfiling/AttachHis/7b31ee6f-950e-4ac8-aa97-d9bbdb16398e.pdf","attachmentBytes":776385,"pdfFlag":true,"newsId":"d850cc57-a382-4121-b22b-538dbfad238c"},{"symbol":"LAL","scripCode":"540952","company":"Lorenzini Apparels Ltd","insider":"","category":"Insider Trading / SAST","type":"","txnType":"","quantity":0,"value":0,"fromDate":"","toDate":"","headline":"Initmation for Closure of Trading Window for the quarter and Nine month ended December 31st 2025.","subcategory":"Closure of Trading Window","intimationDate":"2026-03-27T18:13:57.833","broadcastDate":"2026-03-27T18:13:57.833","attachmentName":"2bf675c9-7bd2-4574-ac4f-e18f58344a3e.pdf","attachmentUrl":"https://www.bseindia.com/xml-data/corpfiling/AttachHis/2bf675c9-7bd2-4574-ac4f-e18f58344a3e.pdf","attachmentBytes":776385,"pdfFlag":true,"newsId":"5c8ee9e3-0812-452d-b0a7-62934d44564b"}]}